svdog/__init__.py
svdog-0.2.4.data/scripts/run_svdog.py
svdog-0.2.4.dist-info/METADATA
svdog-0.2.4.dist-info/WHEEL
svdog-0.2.4.dist-info/top_level.txt
svdog-0.2.4.dist-info/RECORD
