Metadata-Version: 2.1
Name: svdog
Version: 0.2.4
Summary: supervisor's dog, should deploy with flylog
Home-page: https://github.com/dantezhu/svdog
Author: dantezhu
Author-email: dantezhu <zny2008@gmail.com>
License: BSD
Project-URL: Homepage, https://github.com/dantezhu/svdog
Platform: any
Requires-Dist: supervisor
Requires-Dist: flylog
